videogen_mcp/__init__.py
videogen_mcp/router.py
videogen_mcp/server.py
videogen_mcp/clients/__init__.py
videogen_mcp/clients/heygen.py
videogen_mcp/clients/veo.py
videogen_mcp/tools/__init__.py
videogen_mcp/tools/create_avatar_video.py
videogen_mcp/tools/download_video.py
videogen_mcp/tools/generate_creative_video.py
videogen_mcp/tools/generate_from_template.py
videogen_mcp/tools/generate_video.py
videogen_mcp/tools/generate_video_from_image.py
videogen_mcp/tools/get_template_details.py
videogen_mcp/tools/get_video_status.py
videogen_mcp/tools/list_avatars.py
videogen_mcp/tools/list_templates.py
videogen_mcp/tools/list_voices.py
m2ai_mcp_videogen_advisor-1.0.0.dist-info/METADATA
m2ai_mcp_videogen_advisor-1.0.0.dist-info/WHEEL
m2ai_mcp_videogen_advisor-1.0.0.dist-info/entry_points.txt
m2ai_mcp_videogen_advisor-1.0.0.dist-info/licenses/LICENSE
m2ai_mcp_videogen_advisor-1.0.0.dist-info/RECORD
