Metadata-Version: 2.4
Name: m2ai-mcp-videogen-advisor
Version: 1.0.0
Summary: Unified MCP server for video generation with intelligent HeyGen/Veo routing
Project-URL: Homepage, https://github.com/m2ai-mcp-servers/videogen-mcp
Project-URL: Documentation, https://github.com/m2ai-mcp-servers/videogen-mcp#readme
Project-URL: Repository, https://github.com/m2ai-mcp-servers/videogen-mcp
Author: Me, Myself Plus AI LLC
License: MIT
License-File: LICENSE
Keywords: ai,claude,gemini,heygen,mcp,model-context-protocol,veo,video
Classifier: Development Status :: 4 - Beta
Classifier: Intended Audience :: Developers
Classifier: License :: OSI Approved :: MIT License
Classifier: Programming Language :: Python :: 3
Classifier: Programming Language :: Python :: 3.11
Classifier: Programming Language :: Python :: 3.12
Requires-Python: >=3.11
Requires-Dist: httpx>=0.27.0
Requires-Dist: mcp>=1.0.0
Requires-Dist: pydantic>=2.0.0
Provides-Extra: dev
Requires-Dist: mypy>=1.8.0; extra == 'dev'
Requires-Dist: pytest-asyncio>=0.23.0; extra == 'dev'
Requires-Dist: pytest-cov>=4.0.0; extra == 'dev'
Requires-Dist: pytest>=8.0.0; extra == 'dev'
Requires-Dist: respx>=0.21.0; extra == 'dev'
Requires-Dist: ruff>=0.1.0; extra == 'dev'
